redman/__init__.py
redman/__main__.py
redman/cli.py
redman/config.py
redman/history.py
redman/helpers/__init__.py
redman/helpers/color.py
redman/helpers/fzf.py
redman/helpers/redmine_api.py
redman/helpers/table.py
redman-0.1.0.dist-info/LICENSE
redman-0.1.0.dist-info/METADATA
redman-0.1.0.dist-info/WHEEL
redman-0.1.0.dist-info/entry_points.txt
redman-0.1.0.dist-info/top_level.txt
redman-0.1.0.dist-info/RECORD
