Metadata-Version: 2.1
Name: redman
Version: 0.1.0
Summary: REDMAN is a command line tool that manages redmine.
Home-page: UNKNOWN
Author: oktntko
Author-email: oktntko@gmail.com
License: UNKNOWN
Platform: UNKNOWN
Classifier: Development Status :: 1 - Planning
Classifier: License :: OSI Approved :: MIT License
Classifier: Programming Language :: Python :: 3.9
License-File: LICENSE
Requires-Dist: texttable (>=1.6)
Requires-Dist: pyyaml (>=5.4)
Requires-Dist: click (>=8.0)
